README.md
pyproject.toml
setup.py
django_simple_excel.egg-info/PKG-INFO
django_simple_excel.egg-info/SOURCES.txt
django_simple_excel.egg-info/dependency_links.txt
django_simple_excel.egg-info/not-zip-safe
django_simple_excel.egg-info/requires.txt
django_simple_excel.egg-info/top_level.txt
simple_excel/__init__.py
simple_excel/admin.py
simple_excel/apps.py
simple_excel/base.py
simple_excel/engines.py
simple_excel/models.py
simple_excel/tests.py
simple_excel/urls.py
simple_excel/views.py