Metadata-Version: 2.1
Name: django-simple-excel
Version: 0.1.0
Summary: Simple package for export from django model to excel
Home-page: https://github.com/adilet-web-dev/django-simple-excel
Author: adilet-web-dev
License: Creative Commons Attribution 3.0 Unported
Platform: UNKNOWN
Classifier: Framework :: Django :: 3.2
Classifier: Framework :: Django :: 4.0
Classifier: Intended Audience :: Developers
Classifier: Operating System :: OS Independent
Classifier: Programming Language :: Python
Classifier: Programming Language :: Python :: 3
Classifier: Programming Language :: Python :: 3.6
Classifier: Programming Language :: Python :: 3.7
Classifier: Programming Language :: Python :: 3.8
Classifier: Programming Language :: Python :: 3.9
Requires-Python: >=3.6
